grasptext.py
grasptext-0.0.2.dist-info/METADATA
grasptext-0.0.2.dist-info/RECORD
grasptext-0.0.2.dist-info/WHEEL
grasptext-0.0.2.dist-info/top_level.txt
