Metadata-Version: 2.1
Name: grasptext
Version: 0.0.2
Summary: GReedy Augmented Sequential Patterns: an algorithm for extracting patterns from text data
Home-page: https://github.com/plkumjorn/GrASP
Author: Piyawat Lertvittayakumjorn
Author-email: plkumjorn@gmail.com
License: UNKNOWN
Platform: UNKNOWN
Classifier: Programming Language :: Python :: 3
Classifier: Programming Language :: Python :: 3.6
Classifier: Programming Language :: Python :: 3.7
Classifier: License :: OSI Approved :: BSD License
Classifier: Operating System :: OS Independent
Provides-Extra: dev
Requires-Dist: numpy (>=1.16.3)
Requires-Dist: scikit-learn (>=0.23.2)
Requires-Dist: nltk (>=3.2.4)
Requires-Dist: spacy (>=2.0.12)
Requires-Dist: termcolor (>=1.1.0)
Requires-Dist: tqdm (>=4.46.0)
Requires-Dist: Flask (>=0.12.2)
Requires-Dist: patool
Provides-Extra: dev
Requires-Dist: pytest (>=3.7); extra == 'dev'
Requires-Dist: check-manifest; extra == 'dev'
Requires-Dist: twine; extra == 'dev'
